pagination/__init__.py
pagination/pagination.py
pyf_pagination-0.1.dist-info/METADATA
pyf_pagination-0.1.dist-info/WHEEL
pyf_pagination-0.1.dist-info/top_level.txt
pyf_pagination-0.1.dist-info/RECORD
